apachetomcatscanner/Config.py
apachetomcatscanner/Reporter.py
apachetomcatscanner/VulnerabilitiesDB.py
apachetomcatscanner/__init__.py
apachetomcatscanner/__main__.py
apachetomcatscanner/data/credentials.json
apachetomcatscanner/data/update_db.py
apachetomcatscanner/data/vulnerabilities/2000/CVE-2000-0672.json
apachetomcatscanner/data/vulnerabilities/2000/CVE-2000-0759.json
apachetomcatscanner/data/vulnerabilities/2000/CVE-2000-0760.json
apachetomcatscanner/data/vulnerabilities/2001/CVE-2001-0829.json
apachetomcatscanner/data/vulnerabilities/2001/CVE-2001-0917.json
apachetomcatscanner/data/vulnerabilities/2001/CVE-2001-1563.json
apachetomcatscanner/data/vulnerabilities/2002/CVE-2002-0682.json
apachetomcatscanner/data/vulnerabilities/2002/CVE-2002-0935.json
apachetomcatscanner/data/vulnerabilities/2002/CVE-2002-0936.json
apachetomcatscanner/data/vulnerabilities/2002/CVE-2002-1148.json
apachetomcatscanner/data/vulnerabilities/2002/CVE-2002-1394.json
apachetomcatscanner/data/vulnerabilities/2002/CVE-2002-1567.json
apachetomcatscanner/data/vulnerabilities/2002/CVE-2002-1895.json
apachetomcatscanner/data/vulnerabilities/2002/CVE-2002-2006.json
apachetomcatscanner/data/vulnerabilities/2002/CVE-2002-2007.json
apachetomcatscanner/data/vulnerabilities/2002/CVE-2002-2008.json
apachetomcatscanner/data/vulnerabilities/2002/CVE-2002-2009.json
apachetomcatscanner/data/vulnerabilities/2002/CVE-2002-2272.json
apachetomcatscanner/data/vulnerabilities/2003/CVE-2003-0042.json
apachetomcatscanner/data/vulnerabilities/2003/CVE-2003-0043.json
apachetomcatscanner/data/vulnerabilities/2003/CVE-2003-0044.json
apachetomcatscanner/data/vulnerabilities/2003/CVE-2003-0045.json
apachetomcatscanner/data/vulnerabilities/2003/CVE-2003-0866.json
apachetomcatscanner/data/vulnerabilities/2005/CVE-2005-0808.json
apachetomcatscanner/data/vulnerabilities/2005/CVE-2005-2090.json
apachetomcatscanner/data/vulnerabilities/2005/CVE-2005-3510.json
apachetomcatscanner-3.8.0.dist-info/licenses/LICENSE
apachetomcatscanner-3.8.0.dist-info/METADATA
apachetomcatscanner-3.8.0.dist-info/WHEEL
apachetomcatscanner-3.8.0.dist-info/entry_points.txt
apachetomcatscanner-3.8.0.dist-info/top_level.txt
apachetomcatscanner-3.8.0.dist-info/RECORD
