Metadata-Version: 2.4
Name: apachetomcatscanner
Version: 3.8.0
Home-page: https://github.com/p0dalirius/ApacheTomcatScanner
Author: Podalirius
Author-email: podalirius@protonmail.com
License: GPL2
Project-URL: repository, https://github.com/p0dalirius/ApacheTomcatScanner
Classifier: Programming Language :: Python :: 3
Classifier: License :: OSI Approved :: GNU General Public License v2 (GPLv2)
Classifier: Operating System :: OS Independent
Requires-Python: >=3.6
License-File: LICENSE
Requires-Dist: sectools>=1.3.10
Requires-Dist: xlsxwriter
Requires-Dist: urllib3==1.26.16
Requires-Dist: requests==2.29.0
Provides-Extra: build
Requires-Dist: build; extra == "build"
Provides-Extra: twine
Requires-Dist: twine; extra == "twine"
Dynamic: author
Dynamic: home-page
Dynamic: license-file
Dynamic: requires-python
